hyve/__init__.py
hyve/const.py
hyve/elements.py
hyve/flows.py
hyve/layout.py
hyve/plot.py
hyve/prim.py
hyve/transforms.py
hyve/util.py
hyve/data/.DS_Store
hyve/data/cmap/.DS_Store
hyve/data/cmap/tpl-fsLR_hemi-L_desc-modal_rgba.gii
hyve/data/cmap/tpl-fsLR_hemi-L_desc-network_rgba.gii
hyve/data/cmap/tpl-fsLR_hemi-R_desc-modal_rgba.gii
hyve/data/cmap/tpl-fsLR_hemi-R_desc-network_rgba.gii
hyve/data/cmap/tpl-fsaverage_hemi-L_desc-modal_rgba.gii
hyve/data/cmap/tpl-fsaverage_hemi-L_desc-network_rgba.gii
hyve/data/cmap/tpl-fsaverage_hemi-R_desc-modal_rgba.gii
hyve/data/cmap/tpl-fsaverage_hemi-R_desc-network_rgba.gii
hyve/geom/__init__.py
hyve/geom/base.py
hyve/geom/network.py
hyve/geom/points.py
hyve/geom/prim.py
hyve/geom/surf.py
hyve/geom/transforms.py
hyve-0.1.0.dist-info/LICENSE
hyve-0.1.0.dist-info/METADATA
hyve-0.1.0.dist-info/WHEEL
hyve-0.1.0.dist-info/top_level.txt
hyve-0.1.0.dist-info/RECORD
