Metadata-Version: 2.1
Name: hyve
Version: 0.1.0
Summary: Interactive and static 3D visualisation for functional brain mapping
Author-email: Rastko Ciric <rastko@stanford.edu>
Maintainer-email: Rastko Ciric <rastko@stanford.edu>
License: Apache License
Project-URL: Homepage, https://github.com/hypercoil/hyve
Classifier: Programming Language :: Python :: 3
Classifier: License :: OSI Approved :: Apache Software License
Classifier: Operating System :: POSIX :: Linux
Classifier: Operating System :: MacOS :: MacOS X
Requires-Python: >=3.10
License-File: LICENSE
Requires-Dist: conveyant
Requires-Dist: lytemaps
Requires-Dist: matplotlib
Requires-Dist: nibabel
Requires-Dist: numpy
Requires-Dist: pandas
Requires-Dist: pyvista[all]
Requires-Dist: scipy
Requires-Dist: svg.py
Requires-Dist: templateflow
Provides-Extra: test
Requires-Dist: hyve-examples ; extra == 'test'
Requires-Dist: coverage[toml] ; extra == 'test'
Requires-Dist: pytest ; extra == 'test'
Requires-Dist: pytest-cov ; extra == 'test'
Requires-Dist: ruff ; extra == 'test'
Requires-Dist: seaborn ; extra == 'test'
